preprocessor/__init__.py
preprocessor/preprocessor.py
config_preprocessor-0.0.7.dist-info/LICENSE.txt
config_preprocessor-0.0.7.dist-info/METADATA
config_preprocessor-0.0.7.dist-info/WHEEL
config_preprocessor-0.0.7.dist-info/top_level.txt
config_preprocessor-0.0.7.dist-info/RECORD
