Metadata-Version: 2.1
Name: config-preprocessor
Version: 0.0.7
Summary: A
Author: Techer
Author-email: carlos.escalona@techer.com.br
Classifier: Programming Language :: Python :: 3
Classifier: License :: OSI Approved :: MIT License
Classifier: Operating System :: OS Independent
Requires-Python: >=3.6
License-File: LICENSE.txt
Requires-Dist: boto3
Requires-Dist: Jinja2
